[
  {
    "id": 1,
    "timestamp": "363s",
    "labeled_speaker": "委員長",
    "quote": "皆さんに聞いていただきさんどうですか?",
    "check_type": "指名整合",
    "reason": "委員長が「いただきさん」と指名しているが、参加者リストに該当する委員がいないため、聞き間違いか不自然な指名である可能性が高い。",
    "suggested_speaker": "不明",
    "confidence": "高",
    "action": "要人間確認",
    "chunk": 1
  },
  {
    "id": 1,
    "timestamp": "1641s",
    "labeled_speaker": "片山かおる",
    "quote": "えっとですね、吉良さんのですね、通年でパックの数が足りないのかということなんですけれども",
    "check_type": "指名整合",
    "reason": "直前の指名がなく、他の委員の質問を繰り返す形で発言が始まっているため、発言の開始点や進行役の発言との区切りに疑義がある。",
    "suggested_speaker": "不明",
    "confidence": "中",
    "action": "ブロック分割|要人間確認",
    "chunk": 4
  },
  {
    "id": 1,
    "timestamp": "不明",
    "labeled_speaker": "委員長",
    "quote": "初の関係、体制等も含めて、要求委員と調整の上、提出できるものについては提出いたします。",
    "check_type": "指名整合",
    "reason": "委員長が学校教育部長を指名した直後の発言だが、内容が市役所側の答弁（資料提出の調整）であり、進行役である委員長の発言としては不自然。学校教育部長の発言の可能性が高い。",
    "suggested_speaker": "学校教育部長",
    "confidence": "高",
    "action": "ブロック分割|ラベル変更",
    "chunk": 8
  },
  {
    "id": 1,
    "timestamp": "3302",
    "labeled_speaker": "委員長",
    "quote": "はい。学校教育部長。初の関係、体制等も含めて、要求委員と調整の上、提出できるものは調整し提出させていただきたいと存じます。以上です。",
    "check_type": "立場整合",
    "reason": "委員長が学校教育部長を指名した後、指名された学校教育部長が答弁しているように読める。委員長の立場として答弁内容が不自然。",
    "suggested_speaker": "学校教育部長",
    "confidence": "高",
    "action": "ブロック分割",
    "chunk": 9
  },
  {
    "id": 2,
    "timestamp": "3529",
    "labeled_speaker": "委員長",
    "quote": "はい。次は水上さん。",
    "check_type": "指名整合",
    "reason": "参加者リストに「水上さん」という委員は存在しない。「水谷たかこ」委員の誤記の可能性が高い。",
    "suggested_speaker": "委員長",
    "confidence": "高",
    "action": "要人間確認",
    "chunk": 9
  },
  {
    "id": 1,
    "timestamp": "4317s",
    "labeled_speaker": "指導師長",
    "quote": "◯指導師長",
    "check_type": "帰属語整合",
    "reason": "参加者リストに「指導師長」という役職はなく、「学校教育部」の「指導室長」の誤記の可能性が高い。",
    "suggested_speaker": "指導室長",
    "confidence": "高",
    "action": "ラベル変更",
    "chunk": 12
  },
  {
    "id": 1,
    "timestamp": "1:17:49",
    "labeled_speaker": "不明",
    "quote": "はい。森戸委員からのご質問で、学校図書館への本の予算を増やせないかということですが、現状、こちらにつきましては、各14校とも学校図書館図書標準という、クラスごとにこれ、クラスに応じたその書籍数の基準というのが国によって定められておりますけれども、そういった基準も重足しているということもございますし、あと、各課からそういった強い要望というも現在のところ聞いてはおりませんので、引き続き今の体制で学校図書館の充実には努めたいという風に考えております。以上です。",
    "check_type": "指名整合",
    "reason": "発言者ラベルが欠落している。森戸委員の質問に対する答弁であり、直後の発言者から生涯学習課長である可能性が高い。",
    "suggested_speaker": "生涯学習課長",
    "confidence": "高",
    "action": "ラベル変更",
    "chunk": 13
  },
  {
    "id": 2,
    "timestamp": "不明",
    "labeled_speaker": "（呼ぶ声）",
    "quote": "あ、費がどうなん？",
    "check_type": "応答整合",
    "reason": "直後の生涯学習課長の発言で「水谷議員からご質問で」と応答されており、この発言が水谷たかこ委員である可能性が高い。",
    "suggested_speaker": "水谷たかこ",
    "confidence": "高",
    "action": "ラベル変更",
    "chunk": 13
  },
  {
    "id": 3,
    "timestamp": "不明",
    "labeled_speaker": "（呼ぶ声）",
    "quote": "あの、裁量で色々できるものなのか。",
    "check_type": "応答整合",
    "reason": "直前の発言が水谷委員の可能性が高く、その質問の続きと推測される。直後の生涯学習課長の発言もこの質問への応答と見られる。",
    "suggested_speaker": "水谷たかこ",
    "confidence": "中",
    "action": "ラベル変更",
    "chunk": 13
  },
  {
    "id": 4,
    "timestamp": "不明",
    "labeled_speaker": "（呼ぶ声）",
    "quote": "はい。よっていいです。はい。",
    "check_type": "応答整合",
    "reason": "直前の質問者が水谷委員の可能性が高く、その答弁を了解した発言と推測される。",
    "suggested_speaker": "水谷たかこ",
    "confidence": "中",
    "action": "ラベル変更",
    "chunk": 13
  },
  {
    "id": 1,
    "timestamp": "1:23:30",
    "labeled_speaker": "不明",
    "quote": "検討する必要があるんじゃないかという風に思いますが、そういうところも含めて、ちょっと指導室も含めてですね、検討をしていただきたいと思いますが、いかがでしょうか。",
    "check_type": "指名整合",
    "reason": "委員長が「水谷委員」と指名する直前の発言ブロックに発言者ラベルがなく、一連の質問として「以上です」で締めくくられているため、水谷委員の発言である可能性が高い。",
    "suggested_speaker": "水谷たかこ",
    "confidence": "高",
    "action": "ラベル変更",
    "chunk": 14
  },
  {
    "id": 2,
    "timestamp": "1:24:01",
    "labeled_speaker": "不明",
    "quote": "それと今後の学級編成によるクラスの増の問題です。これからさらに増えていくわけですよね、人口が。",
    "check_type": "指名整合",
    "reason": "委員長が「水谷委員」と指名する直前の発言ブロックに発言者ラベルがなく、一連の質問として「以上です」で締めくくられているため、水谷委員の発言である可能性が高い。",
    "suggested_speaker": "水谷たかこ",
    "confidence": "高",
    "action": "ラベル変更",
    "chunk": 14
  },
  {
    "id": 3,
    "timestamp": "1:24:32",
    "labeled_speaker": "不明",
    "quote": "その時にじゃあ図書館としてはどういう体制でやっていくのか、そこのやっぱり体制もしっかり考えていただきたいと思うんですよ。",
    "check_type": "指名整合",
    "reason": "委員長が「水谷委員」と指名する直前の発言ブロックに発言者ラベルがなく、一連の質問として「以上です」で締めくくられているため、水谷委員の発言である可能性が高い。",
    "suggested_speaker": "水谷たかこ",
    "confidence": "高",
    "action": "ラベル変更",
    "chunk": 14
  },
  {
    "id": 1,
    "timestamp": "動画 1:28:40 再生",
    "labeled_speaker": "不明",
    "quote": "のような登録団体なのかということについても少し分かるような形で作成していただければと思います。",
    "check_type": "応答整合",
    "reason": "直後の生涯学習課長の発言で「森戸議員と、片山議員からの最後のご質問だと思います。」と応答されており、また「片山議員がおっしゃった通り」と引用されていることから、このラベルなしの発言が片山委員の質問である可能性が高い。",
    "suggested_speaker": "片山委員",
    "confidence": "中",
    "action": "ラベル変更",
    "chunk": 15
  },
  {
    "id": 1,
    "timestamp": "5525",
    "labeled_speaker": "不明",
    "quote": "先日PTA連合会の総会にも参加をさせていただいて、残念ながらPTAが作れなかった学校も存在をしているわけですね。",
    "check_type": "指名整合",
    "reason": "委員長が水谷委員を指名する直前の発言だが、内容が水谷委員のその後の発言（PTA連合会からの出向経験など）と強く関連しており、水谷委員の発言である可能性が高い。",
    "suggested_speaker": "水谷委員",
    "confidence": "高",
    "action": "ラベル変更",
    "chunk": 16
  },
  {
    "id": 2,
    "timestamp": "5556",
    "labeled_speaker": "不明",
    "quote": "やっぱり子育て世代の保護者の皆さんを支援する体制というのは、やりたいというこの気持ちを大切にする支援体制をあの作ることが今必要なのかなということを痛感していますので、ぜひそこは今後ご検討いただきたいということは今日時点では申し上げておきたいと思います。以上です。",
    "check_type": "指名整合",
    "reason": "上記のブロックと連続しており、内容も水谷委員のその後の発言と強く関連しているため、水谷委員の発言である可能性が高い。",
    "suggested_speaker": "水谷委員",
    "confidence": "高",
    "action": "ラベル変更",
    "chunk": 16
  },
  {
    "id": 1,
    "timestamp": "6567",
    "labeled_speaker": "不明",
    "quote": "休憩を終え、再開いたします。休憩前に引き続き、陳情第16号",
    "check_type": "指名整合",
    "reason": "議事の再開と議題の提示、質疑開始の宣言であり、進行役である委員長の発言と思われるが、発言者ラベルが欠落している。",
    "suggested_speaker": "委員長",
    "confidence": "高",
    "action": "ラベル変更",
    "chunk": 19
  },
  {
    "id": 1,
    "timestamp": "動画 2:03:12 再生",
    "labeled_speaker": "不明",
    "quote": "行く途中なのですが、それぞれ安全確保は、実際計画的に、教員が実施調査というのを事前に行っていますので、その安全確保した上でその工程を計画通りに進んでいるところです。",
    "check_type": "指名整合",
    "reason": "直前に発言者の指名がなく、発言者ラベルも欠落しているため、誰の発言か不明。内容から市役所側の答弁と推測される。",
    "suggested_speaker": "指導室長",
    "confidence": "高",
    "action": "ラベル変更",
    "chunk": 21
  },
  {
    "id": 2,
    "timestamp": "動画 2:04:49 再生",
    "labeled_speaker": "不明",
    "quote": "最後の質問が、教育基本法の第16条についてでございます。ここについては、一般質問の中でも答弁した内容にはなっておりますが、教育基本法の第16条では、教育は不当な支配に服することなく、この法律及び他の法律の定めるところにより行われるべきものであり、教育行政は国と地方公共団体との適切な役割分担及び相互の協力のもと、公正かつ適正に行われなければならないと規定されております。",
    "check_type": "指名整合",
    "reason": "直前に発言者の指名がなく、発言者ラベルも欠落しているため、誰の発言か不明。内容から市役所側の答弁と推測される。",
    "suggested_speaker": "指導室長",
    "confidence": "高",
    "action": "ラベル変更",
    "chunk": 21
  },
  {
    "id": 3,
    "timestamp": "動画 06:20 再生",
    "labeled_speaker": "村上ようすけ",
    "quote": "意見といたします。次の方、たゆさん。",
    "check_type": "立場整合",
    "reason": "村上議員の発言ブロックの最後に、次の発言者を指名する委員長の発言が含まれている。発言者が途中で交代している可能性が高い。",
    "suggested_speaker": "委員長",
    "confidence": "高",
    "action": "ブロック分割",
    "chunk": 21
  },
  {
    "id": 2,
    "timestamp": "411",
    "labeled_speaker": "たゆ久貴",
    "quote": "はい。先ほど、〇〇も伺わせていただきました。",
    "check_type": "指名整合",
    "reason": "参加者リストによると、たゆ久貴氏は本委員会の委員ではない。直前の指名者（村上ようすけ）も進行役ではないため、指名自体に疑義がある。",
    "suggested_speaker": "不明",
    "confidence": "高",
    "action": "要人間確認",
    "chunk": 22
  },
  {
    "id": 3,
    "timestamp": "537",
    "labeled_speaker": "たゆ久貴",
    "quote": "私も沖縄の辺野古の基地建設予定地に現地に足を踏み入れました。",
    "check_type": "一人称整合",
    "reason": "参加者リストによると、たゆ久貴氏は本委員会の委員ではない。この発言は一人称で自身の経験を語っており、委員ではない人物の発言として不自然。",
    "suggested_speaker": "不明",
    "confidence": "高",
    "action": "要人間確認",
    "chunk": 22
  },
  {
    "id": 1,
    "timestamp": "動画 12:40 再生",
    "labeled_speaker": "",
    "quote": "私は大変問題があると考えておりますので、この陳情については〇〇という立場で態度を取っていきたいと思います。",
    "check_type": "帰属語整合",
    "reason": "発言者ラベルが欠落しており、誰の発言か不明。「〇〇という立場で」という表現も不自然で、発言者の立場が不明瞭。",
    "suggested_speaker": "不明",
    "confidence": "高",
    "action": "要人間確認",
    "chunk": 23
  },
  {
    "id": 2,
    "timestamp": "動画 15:49 再生",
    "labeled_speaker": "指導出長",
    "quote": "はい。まず文部科学省からの通知につきましては、東京都教育委員会を通して小金井市の方にも来ております。",
    "check_type": "指名整合",
    "reason": "参加者リストに「指導出長」という役職はなく、「指導室長」が存在するため、誤記の可能性が高い。",
    "suggested_speaker": "指導室長",
    "confidence": "高",
    "action": "ラベル変更",
    "chunk": 23
  },
  {
    "id": 3,
    "timestamp": "動画 17:42 再生",
    "labeled_speaker": "指導出長",
    "quote": "はい。安全確保のガイドラインというところでございます。まずですね、危機管理マニュアルというものを各学校が作成してございます。",
    "check_type": "指名整合",
    "reason": "参加者リストに「指導出長」という役職はなく、「指導室長」が存在するため、誤記の可能性が高い。",
    "suggested_speaker": "指導室長",
    "confidence": "高",
    "action": "ラベル変更",
    "chunk": 23
  },
  {
    "id": 1,
    "timestamp": "1174s",
    "labeled_speaker": "不明",
    "quote": "じゃあお願いします。再開いたします。お諮りいたします。",
    "check_type": "指名整合",
    "reason": "進行役（委員長）の発言と思われるが、発言者ラベルが欠落している。",
    "suggested_speaker": "委員長",
    "confidence": "高",
    "action": "ラベル変更",
    "chunk": 24
  },
  {
    "id": 2,
    "timestamp": "1184s",
    "labeled_speaker": "不明",
    "quote": "47号小金井市子供の権利の日を制定する条例を議題といたします。",
    "check_type": "指名整合",
    "reason": "進行役（委員長）の発言と思われるが、発言者ラベルが欠落している。",
    "suggested_speaker": "委員長",
    "confidence": "高",
    "action": "ラベル変更",
    "chunk": 24
  },
  {
    "id": 1,
    "timestamp": "1537s",
    "labeled_speaker": "不明",
    "quote": "での権利の規定、いろんな形で示されているということがありまして、そちらについてやっぱりこうしっかりと知ってもらうということが重要かなと思ってます。",
    "check_type": "応答整合",
    "reason": "直後の発言者が「大きく4点ご質問いただきました」と応答しているが、直前の質問者のラベルが欠落しており、発言者の帰属が不明。",
    "suggested_speaker": "不明",
    "confidence": "高",
    "action": "ラベル変更",
    "chunk": 25
  },
  {
    "id": 2,
    "timestamp": "1645s",
    "labeled_speaker": "子ども家庭部参事",
    "quote": "えっと、大きく4点ご質問いただきました。まずは、まさに今ご説明いただいた、子供の権利に関する条例の制定を踏まえた上で、なぜその権利条例の中に、この子供の権利の日を入れなかったのかということでございます。",
    "check_type": "帰属語整合",
    "reason": "参加者リスト（市役所側）に「子ども家庭部参事」という役職が明記されていません。他の役職者（例：子ども家庭部長）との取り違えの可能性があります。",
    "suggested_speaker": "不明",
    "confidence": "中",
    "action": "要人間確認",
    "chunk": 25
  },
  {
    "id": 1,
    "timestamp": "38:18",
    "labeled_speaker": "不明",
    "quote": "11月20日についての周知、なぜこの日だったのかという歴史的な意味、背景をきちんと明記して知らせていただきたい。",
    "check_type": "応答整合",
    "reason": "直後の「子ども家庭部参事」の発言で「今、片山議員の方からもおっしゃられたように」とあり、直前のラベルなし発言が片山議員のものであることを示唆しているため。",
    "suggested_speaker": "片山 かおる",
    "confidence": "高",
    "action": "ラベル変更",
    "chunk": 27
  },
  {
    "id": 1,
    "timestamp": "動画 42:25 再生",
    "labeled_speaker": "不明",
    "quote": "実行委員会につきましては、本来、子ども主体、市民主体というところでは実行委員会ができればとお考えがあるのは、そうだと思いますけれども、この度、この第2回定例会の条例になりましたし、その上で合わせて補正予算を提出していただいて事業を、もう秋に進めるという関係で、事業については市の方で選定させていただきました。",
    "check_type": "応答整合",
    "reason": "直後の片山議員の発言「先ほど実行委員会も設置しないってことではあったんですが」が、このブロックの内容を受けている。内容から市役所側の答弁と推測されるが、ラベルがない。",
    "suggested_speaker": "子ども家庭部参事",
    "confidence": "高",
    "action": "ラベル変更",
    "chunk": 28
  },
  {
    "id": 1,
    "timestamp": "3699",
    "labeled_speaker": "不明",
    "quote": "私の先の答弁が不十分だったと思います。森戸委員がおっしゃったように",
    "check_type": "一人称整合",
    "reason": "発言者ラベルがなく、「私の先の答弁」という一人称が誰を指すか不明。市長の発言から「参事」の可能性あり。",
    "suggested_speaker": "参事",
    "confidence": "中",
    "action": "ラベル変更|要人間確認",
    "chunk": 31
  },
  {
    "id": 1,
    "timestamp": "3959",
    "labeled_speaker": "不明",
    "quote": "小金井の「伸びゆく子どもプラン」でうたっているのは何かというとですね、子どもオンブズパーソン、それから虐待対応事業、スクールカウンセラー、巡回型スクールソーシャルワーカー、教育相談事業。子ども相談・子ども家庭センターということになっています。あと何だっけな。",
    "check_type": "指名整合",
    "reason": "発言ブロックに発言者ラベルがありません。委員長による指名前の発言ですが、誰の発言か不明です。",
    "suggested_speaker": "不明",
    "confidence": "高",
    "action": "要人間確認",
    "chunk": 32
  },
  {
    "id": 2,
    "timestamp": "4085",
    "labeled_speaker": "水谷委員",
    "quote": "小金井をおもしろくする会としてもずっと求めてきたものなので",
    "check_type": "帰属語整合",
    "reason": "発言者「水谷委員」の会派は「みらいのこがねい」ですが、「小金井をおもしろくする会」という団体に言及しており、自身の会派と異なる可能性があります。",
    "suggested_speaker": "不明",
    "confidence": "中",
    "action": "要人間確認",
    "chunk": 32
  },
  {
    "id": 1,
    "timestamp": "4797s",
    "labeled_speaker": "不明",
    "quote": "関連でですね、片山議員からいただきました。保護者の方が、こういった形で、認可の方を探されたりした結果でございますが、この後追いで調査をというようなお話でございますが、4月以降も新規の申請、新規の申請で受付が随時増えている部分もございます。",
    "check_type": "要人間確認",
    "reason": "発言者ラベルが欠落している。内容から市役所側の担当者（保育政策調整担当課長）の答弁と推測される。後の保育政策調整担当課長の発言と内容が連続しているため。",
    "suggested_speaker": "保育政策調整担当課長",
    "confidence": "中",
    "action": "ラベル変更",
    "chunk": 34
  },
  {
    "id": 1,
    "timestamp": "不明",
    "labeled_speaker": "片山かおる",
    "quote": "はい、片山委員。",
    "check_type": "一人称整合",
    "reason": "発言者「片山かおる」が自身を「片山委員」と第三者的に呼んでいるため、不自然です。委員長が指名した発言の可能性もあります。",
    "suggested_speaker": "不明",
    "confidence": "中",
    "action": "要人間確認",
    "chunk": 35
  },
  {
    "id": 1,
    "timestamp": "5551s",
    "labeled_speaker": "保育政策調整担当課長",
    "quote": "保育課長。はい。ご質問いただいたところに、順次ご答弁させていただきます。",
    "check_type": "指名整合",
    "reason": "「保育政策調整担当課長」が「保育課長」と呼びかけた後、自身が答弁を続けているように見える。参加者リストでは両者は別役職であり、発言者が交代している可能性が高い。",
    "suggested_speaker": "保育課長",
    "confidence": "高",
    "action": "ブロック分割|ラベル変更|要人間確認",
    "chunk": 36
  },
  {
    "id": 1,
    "timestamp": "動画 1:54:50 再生",
    "labeled_speaker": "不明",
    "quote": "私の主張としましては、一応このご縁というものが非常に重要なものがあったなと思いますので、この、ご縁が市内に配置されているという中での提案ではあるんですけどもね。",
    "check_type": "応答整合",
    "reason": "動画 2:00:44 再生での委員長の発言「片山さんが終わったんだ」から、休憩前のラベルなしで続いた一連の質問が片山委員のものである可能性が高い。",
    "suggested_speaker": "片山 かおる",
    "confidence": "高",
    "action": "ラベル変更",
    "chunk": 39
  },
  {
    "id": 1,
    "timestamp": "1593",
    "labeled_speaker": "森戸 よう子",
    "quote": "隠れた児童の問題、片山さんからも質問ありまして",
    "check_type": "一人称整合",
    "reason": "発言者ラベルが森戸よう子であるにもかかわらず、ブロック内で「片山さん」という第三者の発言に言及しているため。",
    "suggested_speaker": "不明",
    "confidence": "低",
    "action": "要人間確認",
    "chunk": 43
  },
  {
    "id": 2,
    "timestamp": "1754",
    "labeled_speaker": "森戸 よう子",
    "quote": "それから2つ目にはですね、その多園との交流をかなりおっしゃってたと思うんですよ。",
    "check_type": "一人称整合",
    "reason": "発言者ラベルが森戸よう子であるにもかかわらず、ブロック内で「おっしゃってた」と第三者の発言に言及しているため。",
    "suggested_speaker": "不明",
    "confidence": "低",
    "action": "要人間確認",
    "chunk": 43
  },
  {
    "id": 1,
    "timestamp": "不明",
    "labeled_speaker": "不明",
    "quote": "ご質問、多数いただきましたので、もし漏れがございましたらご指摘いただければと思います。",
    "check_type": "指名整合",
    "reason": "進行役が「保育課長」と指名した直後の発言が、保育課長自身の答弁開始時の挨拶である可能性が高い。現在のテキストでは進行役の発言ブロックの一部として扱われている。",
    "suggested_speaker": "保育課長",
    "confidence": "高",
    "action": "ブロック分割|ラベル変更",
    "chunk": 46
  },
  {
    "id": 1,
    "timestamp": "3047",
    "labeled_speaker": "不明",
    "quote": "続きまして、段階的に縮小している栗の実保育園、桜保育園の他の園との連携はどういった形になっているかというお話でございます。",
    "check_type": "立場整合",
    "reason": "発言者ラベルが欠落しており、発言内容がどの立場の人物によるものか、またその立場が一貫しているか確認できないため。",
    "suggested_speaker": "保育課長",
    "confidence": "高",
    "action": "ラベル変更",
    "chunk": 48
  },
  {
    "id": 2,
    "timestamp": "3248",
    "labeled_speaker": "保育課長",
    "quote": "続きまして、市内の幼稚園の問題について、今現状どうなっているかというご質問をいただきました",
    "check_type": "立場整合",
    "reason": "長い発言ブロック内で、明確に別の議題（幼稚園の問題）への回答に切り替わっており、話者が交代している可能性がある。",
    "suggested_speaker": "不明",
    "confidence": "中",
    "action": "ブロック分割",
    "chunk": 48
  },
  {
    "id": 1,
    "timestamp": "3561",
    "labeled_speaker": "吉良のりこ委員",
    "quote": "それはまた別ですよね。それは別の問題だと思うんだけど。誰？誰？あ、そっか。なんか混乱してる。",
    "check_type": "一人称整合",
    "reason": "発言ブロック内で「誰？誰？」と他者に問いかけており、話者が一時的に交代したか、割り込み発言があった可能性が高い。",
    "suggested_speaker": "不明",
    "confidence": "中",
    "action": "ブロック分割|要人間確認",
    "chunk": 49
  },
  {
    "id": 2,
    "timestamp": "3689",
    "labeled_speaker": "吉良のりこ委員",
    "quote": "ちょっとそのあたり国、そういう集計してますよね。国じゃないのか。",
    "check_type": "一人称整合",
    "reason": "発言ブロック内で「国じゃないのか」と他者に確認を求めているように聞こえ、割り込み発言の可能性を排除できない。",
    "suggested_speaker": "不明",
    "confidence": "低",
    "action": "要人間確認",
    "chunk": 49
  },
  {
    "id": 1,
    "timestamp": "1:03:33",
    "labeled_speaker": "不明",
    "quote": "私はね、やっぱりちょっとね、あの、道義的にもね、問題だ",
    "check_type": "一人称整合",
    "reason": "発言者ラベルが欠落しているため、一人称「私」が誰を指すか不明であり、帰属に疑義がある。",
    "suggested_speaker": "不明",
    "confidence": "高",
    "action": "ラベル変更|要人間確認",
    "chunk": 50
  },
  {
    "id": 2,
    "timestamp": "1:05:11",
    "labeled_speaker": "不明",
    "quote": "私はこれはね問題だと思うんですよ。",
    "check_type": "一人称整合",
    "reason": "発言者ラベルが欠落しているため、一人称「私」が誰を指すか不明であり、帰属に疑義がある。",
    "suggested_speaker": "不明",
    "confidence": "高",
    "action": "ラベル変更|要人間確認",
    "chunk": 50
  },
  {
    "id": 3,
    "timestamp": "1:06:17",
    "labeled_speaker": "不明",
    "quote": "私の恐ろしいと思いますよ。",
    "check_type": "一人称整合",
    "reason": "発言者ラベルが欠落しているため、一人称「私」が誰を指すか不明であり、帰属に疑義がある。",
    "suggested_speaker": "不明",
    "confidence": "高",
    "action": "ラベル変更|要人間確認",
    "chunk": 50
  },
  {
    "id": 4,
    "timestamp": "1:06:47",
    "labeled_speaker": "不明",
    "quote": "私の心配のしすぎだということになるかもしれないけれども",
    "check_type": "一人称整合",
    "reason": "発言者ラベルが欠落しているため、一人称「私」が誰を指すか不明であり、帰属に疑義がある。",
    "suggested_speaker": "不明",
    "confidence": "高",
    "action": "ラベル変更|要人間確認",
    "chunk": 50
  },
  {
    "id": 1,
    "timestamp": "1:13:45",
    "labeled_speaker": "保育政策調整担当課長",
    "quote": "先ほど私が申し上げたのは、例えばもし何かをカウントするのであれば",
    "check_type": "一人称整合",
    "reason": "この発言ブロックが当該発言者の最初の発言であるにもかかわらず「先ほど私が申し上げた」とあるため、文脈の欠落か、発言者の取り違えの可能性が考えられます。",
    "suggested_speaker": "不明",
    "confidence": "低",
    "action": "要人間確認",
    "chunk": 51
  },
  {
    "id": 1,
    "timestamp": "1:23:19",
    "labeled_speaker": "不明",
    "quote": "いただきたいなと思っております。子どもの権利条例では、育ち学ぶ施設での子どもの権利の保障というのが第13条で歌われています。",
    "check_type": "要人間確認",
    "reason": "発言者ラベルが欠落しています。発言の開始点であり、誰の発言か不明です。",
    "suggested_speaker": "不明",
    "confidence": "高",
    "action": "要人間確認",
    "chunk": 54
  },
  {
    "id": 2,
    "timestamp": "1:26:46",
    "labeled_speaker": "不明",
    "quote": "0人ということなんですけれども、待機児童はここまで狭まってきた。隠れた欠員というような言葉も先ほどご説明いただいているところではあるんですけど、私は決員のところで、保育園にとっては経営が大変になってくるので問題なのではないかと思っております。",
    "check_type": "指名整合",
    "reason": "直前の委員長による「遠藤さん」という指名があるにもかかわらず、発言者ラベルが欠落しています。指名された遠藤百合子委員の発言である可能性が高いです。",
    "suggested_speaker": "遠藤 百合子",
    "confidence": "高",
    "action": "ラベル変更",
    "chunk": 54
  },
  {
    "id": 1,
    "timestamp": "5269",
    "labeled_speaker": "不明",
    "quote": "ただ、まず学年で申し上げますと、0歳から2歳クラスまでは、今回の待機児童が発生した状況も踏まえて、各園で目立った欠員というのは発生は、昨年から大幅に減ったなというのが印象でございます。",
    "check_type": "応答整合",
    "reason": "後続の遠藤委員の発言「ご答弁いただきました」から、直前の発言は市役所側からの答弁と推測されるため。",
    "suggested_speaker": "保育政策調整担当課長",
    "confidence": "中",
    "action": "ラベル変更",
    "chunk": 55
  },
  {
    "id": 2,
    "timestamp": "5497",
    "labeled_speaker": "不明",
    "quote": "再開いたします。ここでお諮りいたします。ただ今までの議事の進行状況から考えてしばらく時間延長をいたしたいと思います。これにご異議ありませんか。",
    "check_type": "ブロック分割",
    "reason": "直前の「委員長」の発言と内容が連続しており、議事進行役の発言であるため。",
    "suggested_speaker": "委員長",
    "confidence": "高",
    "action": "ブロック分割",
    "chunk": 55
  },
  {
    "id": 3,
    "timestamp": "5530",
    "labeled_speaker": "不明",
    "quote": "議案第 50号、小金井市特定教育・保育施設及び特定地域型保育事業の運営に関する基準を定める条例の一部を改正する条例につきまして、委員長報告に載せる意見要望がございましたら発言をお願いいたします。",
    "check_type": "ブロック分割",
    "reason": "直前の「委員長」の発言と内容が連続しており、議事進行役の発言であるため。",
    "suggested_speaker": "委員長",
    "confidence": "高",
    "action": "ブロック分割",
    "chunk": 55
  },
  {
    "id": 4,
    "timestamp": "5603",
    "labeled_speaker": "不明",
    "quote": "はい。起立多数。したがって本件は原案可決と決定いたしました。次に、議案第51号、小金井市家庭的保育事業等の設備及び運営に関する基準を定める条例の一部を改正する条例につきまして委員長報告に載せる意見要望がございましたら発言をお願いいたします。",
    "check_type": "ブロック分割",
    "reason": "直前の「委員長」の発言と内容が連続しており、議事進行役の発言であるため。",
    "suggested_speaker": "委員長",
    "confidence": "高",
    "action": "ブロック分割",
    "chunk": 55
  },
  {
    "id": 5,
    "timestamp": "5633",
    "labeled_speaker": "不明",
    "quote": "本件に対する討論を終了することにご異議ありませんか。",
    "check_type": "ブロック分割",
    "reason": "直前の「委員長」の発言と内容が連続しており、議事進行役の発言であるため。",
    "suggested_speaker": "委員長",
    "confidence": "高",
    "action": "ブロック分割",
    "chunk": 55
  },
  {
    "id": 6,
    "timestamp": "5676",
    "labeled_speaker": "不明",
    "quote": "次に議案第52号、小金井市立保育園における乳児等通園支援事業に関する条例の一部を改正する条例につきまして委員長報告に載せる意見要望がございましたら発言をお願いいたします。",
    "check_type": "ブロック分割",
    "reason": "直前の「委員長」の発言と内容が連続しており、議事進行役の発言であるため。",
    "suggested_speaker": "委員長",
    "confidence": "高",
    "action": "ブロック分割",
    "chunk": 55
  },
  {
    "id": 1,
    "timestamp": "6529s",
    "labeled_speaker": "◯自立生活支援課長",
    "quote": "はい。片山委員からございました、次年度繰り越しの関係で、答弁の方させていただきます。",
    "check_type": "応答整合",
    "reason": "自立生活支援課長が「片山委員からございました」と応答しているが、直前の発言ブロックのラベルは「地域福祉課長」であり、言及された人物と直前のラベルが一致しないため。",
    "suggested_speaker": "不明",
    "confidence": "高",
    "action": "要人間確認",
    "chunk": 58
  },
  {
    "id": 1,
    "timestamp": "7397s",
    "labeled_speaker": "委員長",
    "quote": "本日はご覧いただきありがとうございます。",
    "check_type": "立場整合",
    "reason": "委員長が会議中に視聴者へ向けた挨拶をするのは不自然であり、直前の休憩指示とも文脈が繋がらないため、発言者が異なる可能性が高い。",
    "suggested_speaker": "不明",
    "confidence": "高",
    "action": "ブロック分割|ラベル変更|要人間確認",
    "chunk": 60
  },
  {
    "id": 1,
    "timestamp": "動画 23:07 再生",
    "labeled_speaker": "不明",
    "quote": "先日伺った中でも、各自治体がいろんな取り組みを行っていらっしゃるというのもよく勉強されていて、私は本当に勉強になりました。",
    "check_type": "応答整合",
    "reason": "委員長が後続の発言（動画 31:04 再生）で「森戸委員」を指名しており、その直前の一連の質問者と推測されるが、発言者ラベルがない。",
    "suggested_speaker": "森戸よう子",
    "confidence": "高",
    "action": "ラベル変更",
    "chunk": 64
  },
  {
    "id": 1,
    "timestamp": "2334",
    "labeled_speaker": "森戸 よう子",
    "quote": "このところは終了で、継続調査をしたいと思いますね。いいですか。",
    "check_type": "立場整合",
    "reason": "委員である森戸よう子氏が議事進行役のような発言をしているため、話者が異なる可能性、または発言ブロックの分割が必要な可能性。",
    "suggested_speaker": "委員長",
    "confidence": "高",
    "action": "ブロック分割",
    "chunk": 66
  },
  {
    "id": 1,
    "timestamp": "3044s",
    "labeled_speaker": "不明",
    "quote": "それが重要ですよという指摘があったりとかですね、そういった点もございました。",
    "check_type": "応答整合",
    "reason": "後続の村上委員の発言「ご答弁いただきました」に対する答弁と推測されるが、発言者ラベルが欠落しているため。",
    "suggested_speaker": "市役所側担当者",
    "confidence": "高",
    "action": "要人間確認",
    "chunk": 69
  },
  {
    "id": 2,
    "timestamp": "3076s",
    "labeled_speaker": "不明",
    "quote": "資料にございますように、7月に予定しております保護者会にては、この第三者評価の結果も受けまして、",
    "check_type": "応答整合",
    "reason": "後続の村上委員の発言「ご答弁いただきました」に対する答弁と推測されるが、発言者ラベルが欠落しているため。",
    "suggested_speaker": "市役所側担当者",
    "confidence": "高",
    "action": "要人間確認",
    "chunk": 69
  },
  {
    "id": 1,
    "timestamp": "動画 1:00:28 再生",
    "labeled_speaker": "村上",
    "quote": "つまり、先ほど村上さんがおっしゃった情報連携ができていないんですよ。",
    "check_type": "一人称整合",
    "reason": "発言者ラベルが「村上」であるにもかかわらず、発言内容中に「先ほど村上さんがおっしゃった」と第三者的に言及されているため、この部分で話者が交代している可能性が高い。",
    "suggested_speaker": "不明",
    "confidence": "高",
    "action": "ブロック分割|ラベル変更|要人間確認",
    "chunk": 71
  },
  {
    "id": 1,
    "timestamp": "4436",
    "labeled_speaker": "不明",
    "quote": "また待遇の面というところもありますが、この辺はなかなか民設民営のところでございますので、しっかり課題については共有をさせていただきたいと思ってはございますが、具体の待遇改善についてはしっかり話し合えることは話してみたいと思います。",
    "check_type": "指名整合",
    "reason": "発言ブロックにラベルがなく、誰の発言か不明。直後の発言が市長であるため、このブロックも市長の発言である可能性が高い。",
    "suggested_speaker": "市長",
    "confidence": "高",
    "action": "ラベル変更",
    "chunk": 74
  },
  {
    "id": 2,
    "timestamp": "4684",
    "labeled_speaker": "議長",
    "quote": "◯議長　〇〇議員。",
    "check_type": "指名整合",
    "reason": "議長が「〇〇議員」と指名しているが、具体的な議員名が不明であり、次の発言ブロックのラベル付けに支障がある。",
    "suggested_speaker": "不明",
    "confidence": "高",
    "action": "要人間確認",
    "chunk": 74
  },
  {
    "id": 1,
    "timestamp": "4729",
    "labeled_speaker": "〇〇〇議員",
    "quote": "1点目のメガロスの問題であります。",
    "check_type": "指名整合",
    "reason": "議長が「〇〇議員」と指名しているが、発言者ラベルが「〇〇〇議員」となっており、指名された人物が不明。",
    "suggested_speaker": "不明",
    "confidence": "高",
    "action": "要人間確認",
    "chunk": 75
  },
  {
    "id": 2,
    "timestamp": "4874",
    "labeled_speaker": "〇〇〇議員",
    "quote": "私たち共産党も中長期・短期の計画をしっかりと方針を持つべきだ",
    "check_type": "帰属語整合",
    "reason": "発言者が「私たち共産党」と述べているが、ラベルが「〇〇〇議員」であり、共産党所属の委員（森戸よう子）と一致するか不明。",
    "suggested_speaker": "森戸 よう子",
    "confidence": "高",
    "action": "ラベル変更",
    "chunk": 75
  },
  {
    "id": 3,
    "timestamp": "5054",
    "labeled_speaker": "〇〇〇議員",
    "quote": "先ほど森戸議員がおっしゃったように、こちらの委員会にきちんとした情報を出していただきたいと思います。",
    "check_type": "一人称整合",
    "reason": "発言ブロック内で「先ほど森戸議員がおっしゃったように」とあり、ラベルの人物（〇〇〇議員）が森戸議員である場合、自身を第三者として言及していることになる。",
    "suggested_speaker": "森戸 よう子",
    "confidence": "高",
    "action": "ラベル変更",
    "chunk": 75
  },
  {
    "id": 1,
    "timestamp": "1:23:44",
    "labeled_speaker": "不明",
    "quote": "そしてこの情報開示については、先ほど森戸議員がおっしゃったように",
    "check_type": "応答整合",
    "reason": "発言者ラベルがないブロックで、森戸議員に言及しているため、この発言者は森戸議員ではない。ラベル付与が必要。",
    "suggested_speaker": "不明",
    "confidence": "高",
    "action": "要人間確認",
    "chunk": 76
  },
  {
    "id": 2,
    "timestamp": "1:25:41",
    "labeled_speaker": "不明",
    "quote": "関連するところで申し上げますと、片山議員のご質問の先に概要とかのお知らせということです。",
    "check_type": "応答整合",
    "reason": "発言者ラベルがないブロックで、片山議員に言及しているため、この発言者は片山議員ではない。直前の森戸議員の質問への回答と見られるため、市役所側の人物の可能性が高い。ラベル付与が必要。",
    "suggested_speaker": "子ども家庭部長",
    "confidence": "中",
    "action": "要人間確認",
    "chunk": 76
  },
  {
    "id": 3,
    "timestamp": "1:26:26",
    "labeled_speaker": "不明",
    "quote": "南小学校も入るのかというところも、確か森戸議員が疑問に思われたと思うんですけど。",
    "check_type": "応答整合",
    "reason": "発言者ラベルがないブロックで、森戸議員に言及しているため、この発言者は森戸議員ではない。緑小学校や南小学校に関する説明であり、市役所側の人物の回答と見られる。ラベル付与が必要。",
    "suggested_speaker": "子ども家庭部長",
    "confidence": "中",
    "action": "要人間確認",
    "chunk": 76
  },
  {
    "id": 1,
    "timestamp": "5424",
    "labeled_speaker": "不明",
    "quote": "と認め、本件に対する現時点での質疑を終了いたします。お諮りいたします。",
    "check_type": "指名整合",
    "reason": "直前の「ご異議ありませんか」に対する応答と、その後の議事進行がラベルなしになっているため、委員長の発言である可能性が高い。",
    "suggested_speaker": "委員長",
    "confidence": "高",
    "action": "ラベル変更",
    "chunk": 77
  },
  {
    "id": 2,
    "timestamp": "5456",
    "labeled_speaker": "不明",
    "quote": "と認め、本件は継続調査と決定いたしました。次に行政視察に係る所管事務調査の継続審査議決を行います。",
    "check_type": "指名整合",
    "reason": "直前の「これにご異議ありませんか」に対する応答と、その後の議事進行がラベルなしになっているため、委員長の発言である可能性が高い。",
    "suggested_speaker": "委員長",
    "confidence": "高",
    "action": "ラベル変更",
    "chunk": 77
  },
  {
    "id": 3,
    "timestamp": "5487",
    "labeled_speaker": "不明",
    "quote": "と認めます。したがって、ただいま申し上げたとおり決定いたしました。なお閉会中の委員派遣は、議長に対し委員派遣承認要求を行うこととし、派遣委員、日時、場所、目的及び経費等の手続きについては、委員長にご一任願いたいと思います。",
    "check_type": "指名整合",
    "reason": "直前の「ご異議ありませんか」に対する応答と、その後の議事進行がラベルなしになっているため、委員長の発言である可能性が高い。",
    "suggested_speaker": "委員長",
    "confidence": "高",
    "action": "ラベル変更",
    "chunk": 77
  },
  {
    "id": 4,
    "timestamp": "5487",
    "labeled_speaker": "不明",
    "quote": "これにご異議ありませんか。と認めます。したがって、ただいま申し上げたとおり決定いたしました。次に行政報告を行います。",
    "check_type": "指名整合",
    "reason": "直前の委員長の発言の続きと、その後の議事進行がラベルなしになっているため、委員長の発言である可能性が高い。",
    "suggested_speaker": "委員長",
    "confidence": "高",
    "action": "ラベル変更",
    "chunk": 77
  },
  {
    "id": 5,
    "timestamp": "5621",
    "labeled_speaker": "不明",
    "quote": "と認めます。したがって、本件に対する質疑を終了いたします。 次に行政報告3、公民館利用者向け説明会の開催についてを行います。部局の説明を求めます。",
    "check_type": "指名整合",
    "reason": "直前の「ご異議なし」に対する応答と、その後の議事進行がラベルなしになっているため、委員長の発言である可能性が高い。",
    "suggested_speaker": "委員長",
    "confidence": "高",
    "action": "ラベル変更",
    "chunk": 77
  },
  {
    "id": 6,
    "timestamp": "5654",
    "labeled_speaker": "事業係長",
    "quote": "それでは公民館利用者向け説明会の開催について報告させていただきます。",
    "check_type": "帰属語整合",
    "reason": "「事業係長」という役職が参加者リストに明記されていないため、この人物が誰であるか、または役職名が正しいか確認が必要。",
    "suggested_speaker": "不明",
    "confidence": "低",
    "action": "要人間確認",
    "chunk": 77
  },
  {
    "id": 1,
    "timestamp": "6158",
    "labeled_speaker": "事業係長",
    "quote": "手引きの方なんですが、現状公民館利用のルールで、幸運審に諮ることはしておりません。",
    "check_type": "帰属語整合",
    "reason": "「事業係長」は参加者リストにない役職名です。公民館に関する発言のため、生涯学習部の課長クラスの可能性が高いです。",
    "suggested_speaker": "不明",
    "confidence": "中",
    "action": "要人間確認",
    "chunk": 79
  }
]